[
  {
    "title": "The Cameo",
    "venue": "Edinburgh"
  },
  {
    "title": "Filmhouse",
    "venue": "Filmhouse"
  },
  {
    "title": "Edinburgh Film Guide",
    "venue": "Edinburgh"
  },
  {
    "title": "Luxury  Edinburgh",
    "venue": "Edinburgh"
  },
  {
    "title": "Cameo  (38 Home Street, Edinburgh)",
    "venue": "Edinburgh"
  },
  {
    "title": "Edinburgh cinema listings information",
    "venue": "Edinburgh"
  },
  {
    "title": "Dominion",
    "venue": "Dominion"
  },
  {
    "title": "Edinburgh Omni Centre Lux",
    "venue": "Edinburgh"
  },
  {
    "title": "ODEON Edinburgh Lothian Road",
    "venue": "Edinburgh"
  },
  {
    "title": "Home",
    "venue": "Dominion"
  }
]